simple_extract/__init__.py
simple_extract/__main__.py
simple_extract-0.3.4.dist-info/LICENSE
simple_extract-0.3.4.dist-info/METADATA
simple_extract-0.3.4.dist-info/WHEEL
simple_extract-0.3.4.dist-info/entry_points.txt
simple_extract-0.3.4.dist-info/top_level.txt
simple_extract-0.3.4.dist-info/RECORD
