Metadata-Version: 2.2
Name: simple-extract
Version: 0.3.4
Summary: A small command line utility to help extract compressed archives.
Author-email: Michael Berry <trismegustis@gmail.com>
License: MIT
Project-URL: Homepage, https://github.com/berrym/simple_extract
Classifier: License :: OSI Approved :: MIT License
Classifier: Operating System :: POSIX
Classifier: Programming Language :: Python :: 3
Requires-Python: >=3.12
License-File: LICENSE
